wordlists/__init__.py
wordlists/wordlist.py
wordlists-1.0.0.dist-info/LICENSE
wordlists-1.0.0.dist-info/WHEEL
wordlists-1.0.0.dist-info/METADATA
wordlists-1.0.0.dist-info/RECORD
