Metadata-Version: 2.1
Name: wordlists
Version: 1.0.0
Summary: Utilities to download word lists in Python
Home-page: https://github.com/vcokltfre/wordlists
License: MIT
Author: vcokltfre
Author-email: vcokltfre@gmail.com
Requires-Python: >=3.9,<4.0
Classifier: License :: OSI Approved :: MIT License
Classifier: Programming Language :: Python :: 3
Classifier: Programming Language :: Python :: 3.10
Classifier: Programming Language :: Python :: 3.9
Requires-Dist: requests (>=2.26.0,<3.0.0)
Project-URL: Repository, https://github.com/vcokltfre/wordlists
